guardrail/__init__.py
guardrail/client.py
guardrail/db.py
guardrail/env_config.py
guardrail/dataset/__init__.py
guardrail/dataset/convert_json.py
guardrail/dataset/dataset_creation_local_api.py
guardrail/dataset/dataset_generator.py
guardrail/dataset/embeddings.py
guardrail/dataset/helper.py
guardrail/dataset/parse_pdf.py
guardrail/firewall/__init__.py
guardrail/firewall/firewall.py
guardrail/firewall/util.py
guardrail/firewall/vault.py
guardrail/firewall/input_detectors/__init__.py
guardrail/firewall/input_detectors/anonymize.py
guardrail/firewall/input_detectors/base_detector.py
guardrail/firewall/input_detectors/coding_language.py
guardrail/firewall/input_detectors/dos_tokens.py
guardrail/firewall/input_detectors/harmful.py
guardrail/firewall/input_detectors/language.py
guardrail/firewall/input_detectors/malware_url.py
guardrail/firewall/input_detectors/prompt_injections.py
guardrail/firewall/input_detectors/regex.py
guardrail/firewall/input_detectors/secrets.py
guardrail/firewall/input_detectors/stop_input_substrings.py
guardrail/firewall/input_detectors/text_quality.py
guardrail/firewall/input_detectors/toxicity.py
guardrail/firewall/output_detectors/__init__.py
guardrail/firewall/output_detectors/base_detector.py
guardrail/firewall/output_detectors/bias.py
guardrail/firewall/output_detectors/coding_language.py
guardrail/firewall/output_detectors/deanonymize.py
guardrail/firewall/output_detectors/factual_consistency.py
guardrail/firewall/output_detectors/harmful.py
guardrail/firewall/output_detectors/language.py
guardrail/firewall/output_detectors/malware_url.py
guardrail/firewall/output_detectors/regex.py
guardrail/firewall/output_detectors/relevance.py
guardrail/firewall/output_detectors/sensitive_pii.py
guardrail/firewall/output_detectors/stop_output_substrings.py
guardrail/firewall/output_detectors/text_quality.py
guardrail/firewall/output_detectors/toxicity.py
guardrail/firewall/output_detectors/factuality_detector/__init__.py
guardrail_ml-0.0.16.dist-info/LICENSE.txt
guardrail_ml-0.0.16.dist-info/METADATA
guardrail_ml-0.0.16.dist-info/WHEEL
guardrail_ml-0.0.16.dist-info/top_level.txt
guardrail_ml-0.0.16.dist-info/RECORD
