Metadata-Version: 2.1
Name: guardrail-ml
Version: 0.0.16
Summary: Monitor LLMs with custom metrics to scale with confidence
Home-page: http://www.guardrailml.com
Author: Kevin Wu
Author-email: kevin@guardrailml.com
Classifier: Programming Language :: Python :: 3
Classifier: License :: OSI Approved :: Apache Software License
Classifier: Operating System :: OS Independent
Requires-Python: >=3.6
License-File: LICENSE.txt
Requires-Dist: textstat
Requires-Dist: transformers <=4.30.2
Requires-Dist: sentencepiece
Requires-Dist: sentence-transformers
Requires-Dist: accelerate
Requires-Dist: bitsandbytes
Requires-Dist: cleantext
Requires-Dist: unidecode
Requires-Dist: pillow
Requires-Dist: jsonformer
Requires-Dist: scipy
Requires-Dist: pydantic <=2.0.3
Requires-Dist: tenacity
Requires-Dist: colorama
Requires-Dist: openai
Requires-Dist: python-dotenv
Requires-Dist: einops
Requires-Dist: langchain
Requires-Dist: Faker
Requires-Dist: tensorflow
Requires-Dist: presidio-analyzer <=2.2.33
Requires-Dist: presidio-anonymizer <=2.2.33
Requires-Dist: genbit
Requires-Dist: jsonlines
Requires-Dist: pydantic-settings <=2.0.3
Requires-Dist: detect-secrets
Requires-Dist: tiktoken
Requires-Dist: spacy-transformers
Requires-Dist: fasttextfasttext-langdetect
